mc_server_setup/__init__.py
mc_server_setup/__main__.py
mc_server_setup/main.py
mc_server_setup-2.0.dist-info/METADATA
mc_server_setup-2.0.dist-info/WHEEL
mc_server_setup-2.0.dist-info/entry_points.txt
mc_server_setup-2.0.dist-info/license
mc_server_setup-2.0.dist-info/top_level.txt
mc_server_setup-2.0.dist-info/RECORD
