Metadata-Version: 2.1
Name: mc-server-setup
Version: 2.0
Summary: A Minecraft server setup script made using python3
Home-page: https://github.com/Yot360/mc-server-python
Author: Yot360
Author-email: 65982248+yot360@users.noreply.github.com
Maintainer: Yot360
Maintainer-email: 65982248+yot360@users.noreply.github.com
License: MIT
Download-URL: https://github.com/Yot360/mc-server-python
Project-URL: Bug Tracker, https://github.com/Yot360/mc-server-python/issues
Keywords: minecraft
Platform: Linux
Platform: MacOS
Platform: Windows
Classifier: Development Status :: 4 - Beta
Classifier: Intended Audience :: End Users/Desktop
Classifier: Natural Language :: English
Classifier: Operating System :: MacOS
Classifier: Operating System :: Microsoft :: Windows :: Windows 10
Classifier: Operating System :: POSIX :: Linux
Classifier: License :: OSI Approved :: MIT License
Classifier: Programming Language :: Python
Classifier: Programming Language :: Python :: 3.6
Classifier: Programming Language :: Python :: 3.7
Classifier: Programming Language :: Python :: 3.8
Classifier: Programming Language :: Python :: 3.9
Classifier: Topic :: Games/Entertainment
Classifier: Topic :: Utilities
Requires-Python: >=3.6
License-File: license
Requires-Dist: progressbar (>=2.5)
